kilbourn_modern_python/__init__.py
kilbourn_modern_python/console.py
kilbourn_modern_python/wikipedia.py
kilbourn_modern_python-0.1.0.dist-info/entry_points.txt
kilbourn_modern_python-0.1.0.dist-info/LICENSE
kilbourn_modern_python-0.1.0.dist-info/WHEEL
kilbourn_modern_python-0.1.0.dist-info/METADATA
kilbourn_modern_python-0.1.0.dist-info/RECORD
